CnkiSpider/__init__.py
CnkiSpider/function.py
CnkiSpider/para.py
CnkiSpider/CnkiSpider/CnkiSpider.py
CnkiSpider/CnkiSpider/__init__.py
CnkiSpider-1.1.0.dist-info/LICENSE
CnkiSpider-1.1.0.dist-info/METADATA
CnkiSpider-1.1.0.dist-info/WHEEL
CnkiSpider-1.1.0.dist-info/top_level.txt
CnkiSpider-1.1.0.dist-info/RECORD
