Metadata-Version: 2.1
Name: CnkiSpider
Version: 1.1.0
Summary: CnkiSpider是一个高效爬取知网文章信息的包
Home-page: https://github.com/zemengchuan/CnkiSpider
Author: zemengchuan
Author-email: zemengchuan@gmail.com
License: MIT
Keywords: CNKI,webcrawler,data,lxml
Classifier: Programming Language :: Python :: 3.7
Classifier: Programming Language :: Python :: 3.8
Classifier: Programming Language :: Python :: 3.9
Classifier: Programming Language :: Python :: 3.10
Classifier: Programming Language :: Python :: 3.11
Classifier: License :: OSI Approved :: MIT License
Classifier: Operating System :: OS Independent
Requires-Python: >=3.7
License-File: LICENSE
Requires-Dist: requests
Requires-Dist: pandas
